repo2kook-0.0.2.dist-info/METADATA
repo2kook-0.0.2.dist-info/WHEEL
repo2kook-0.0.2.dist-info/entry_points.txt
repo2kook-0.0.2.dist-info/licenses/LICENSE
repo2kook/__init__.py
repo2kook/config.py
repo2kook/middleware.py
repo2kook/models.py
repo2kook/router.py
repo2kook/templates.py
repo2kook/utils.py
repo2kook-0.0.2.dist-info/RECORD
