Metadata-Version: 2.1
Name: Repo2Kook
Version: 0.0.2
Summary: Send GitHub Webhook to Kook
Author-Email: jingfelix <jingfelix@outlook.com>
License: GPLv3
Project-URL: Homepage, https://github.com/jingfelix/Repo2Kook
Project-URL: Bug Tracker, https://github.com/jingfelix/Repo2Kook
Requires-Python: >=3.10
Requires-Dist: fastapi>=0.105.0
Requires-Dist: httpx>=0.26.0
Requires-Dist: uvicorn>=0.25.0
Requires-Dist: pydantic-settings>=2.1.0
Requires-Dist: python-multipart>=0.0.18
Requires-Dist: urllib3>=2.2.2
